ressetter/__init__.py
ressetter/config.py
ressetter/config.toml
ressetter/display_settings.py
ressetter/input_monitor.py
ressetter/main.py
ressetter/ressetter.py
ressetter-0.1.1.post1.dist-info/METADATA
ressetter-0.1.1.post1.dist-info/WHEEL
ressetter-0.1.1.post1.dist-info/entry_points.txt
ressetter-0.1.1.post1.dist-info/RECORD
