Metadata-Version: 2.3
Name: ressetter
Version: 0.1.1.post1
Summary: Auto-set resolution and refresh rate on Windows
Author: Danny Stewart
Author-email: danny@stewart.cc
Requires-Python: >=3.12,<3.14
Classifier: Programming Language :: Python :: 3
Classifier: Programming Language :: Python :: 3.12
Classifier: Programming Language :: Python :: 3.13
Requires-Dist: dsbase (>=0.4.1,<0.5.0)
Requires-Dist: psutil (>=7.0.0)
Requires-Dist: pynput (>=1.8.1)
Requires-Dist: pywin32 (>=310) ; platform_system == "Windows"
Requires-Dist: toml (>=0.10.2)
